{
  "type": "GROUP",
"name": "Global Information",
"path": "",
"pathFormatted": "group_missing-name-b06d1",
"stats": {
    "name": "Global Information",
    "numberOfRequests": {
        "total": 2,
        "ok": 2,
        "ko": 0
    },
    "minResponseTime": {
        "total": 329,
        "ok": 329,
        "ko": 0
    },
    "maxResponseTime": {
        "total": 1335,
        "ok": 1335,
        "ko": 0
    },
    "meanResponseTime": {
        "total": 832,
        "ok": 832,
        "ko": 0
    },
    "standardDeviation": {
        "total": 503,
        "ok": 503,
        "ko": 0
    },
    "percentiles1": {
        "total": 832,
        "ok": 832,
        "ko": 0
    },
    "percentiles2": {
        "total": 1084,
        "ok": 1084,
        "ko": 0
    },
    "percentiles3": {
        "total": 1285,
        "ok": 1285,
        "ko": 0
    },
    "percentiles4": {
        "total": 1325,
        "ok": 1325,
        "ko": 0
    },
    "group1": {
    "name": "t < 800 ms",
    "count": 1,
    "percentage": 50
},
    "group2": {
    "name": "800 ms < t < 1200 ms",
    "count": 0,
    "percentage": 0
},
    "group3": {
    "name": "t > 1200 ms",
    "count": 1,
    "percentage": 50
},
    "group4": {
    "name": "failed",
    "count": 0,
    "percentage": 0
},
    "meanNumberOfRequestsPerSecond": {
        "total": 0.6666666666666666,
        "ok": 0.6666666666666666,
        "ko": 0
    }
},
"contents": {
"req_go-to-home-page-3116e": {
        "type": "REQUEST",
        "name": "Go to Home Page",
"path": "Go to Home Page",
"pathFormatted": "req_go-to-home-page-3116e",
"stats": {
    "name": "Go to Home Page",
    "numberOfRequests": {
        "total": 1,
        "ok": 1,
        "ko": 0
    },
    "minResponseTime": {
        "total": 1335,
        "ok": 1335,
        "ko": 0
    },
    "maxResponseTime": {
        "total": 1335,
        "ok": 1335,
        "ko": 0
    },
    "meanResponseTime": {
        "total": 1335,
        "ok": 1335,
        "ko": 0
    },
    "standardDeviation": {
        "total": 0,
        "ok": 0,
        "ko": 0
    },
    "percentiles1": {
        "total": 1335,
        "ok": 1335,
        "ko": 0
    },
    "percentiles2": {
        "total": 1335,
        "ok": 1335,
        "ko": 0
    },
    "percentiles3": {
        "total": 1335,
        "ok": 1335,
        "ko": 0
    },
    "percentiles4": {
        "total": 1335,
        "ok": 1335,
        "ko": 0
    },
    "group1": {
    "name": "t < 800 ms",
    "count": 0,
    "percentage": 0
},
    "group2": {
    "name": "800 ms < t < 1200 ms",
    "count": 0,
    "percentage": 0
},
    "group3": {
    "name": "t > 1200 ms",
    "count": 1,
    "percentage": 100
},
    "group4": {
    "name": "failed",
    "count": 0,
    "percentage": 0
},
    "meanNumberOfRequestsPerSecond": {
        "total": 0.3333333333333333,
        "ok": 0.3333333333333333,
        "ko": 0
    }
}
    },"req_go-to-home-page-bba4e": {
        "type": "REQUEST",
        "name": "Go to Home Page Redirect 1",
"path": "Go to Home Page Redirect 1",
"pathFormatted": "req_go-to-home-page-bba4e",
"stats": {
    "name": "Go to Home Page Redirect 1",
    "numberOfRequests": {
        "total": 1,
        "ok": 1,
        "ko": 0
    },
    "minResponseTime": {
        "total": 329,
        "ok": 329,
        "ko": 0
    },
    "maxResponseTime": {
        "total": 329,
        "ok": 329,
        "ko": 0
    },
    "meanResponseTime": {
        "total": 329,
        "ok": 329,
        "ko": 0
    },
    "standardDeviation": {
        "total": 0,
        "ok": 0,
        "ko": 0
    },
    "percentiles1": {
        "total": 329,
        "ok": 329,
        "ko": 0
    },
    "percentiles2": {
        "total": 329,
        "ok": 329,
        "ko": 0
    },
    "percentiles3": {
        "total": 329,
        "ok": 329,
        "ko": 0
    },
    "percentiles4": {
        "total": 329,
        "ok": 329,
        "ko": 0
    },
    "group1": {
    "name": "t < 800 ms",
    "count": 1,
    "percentage": 100
},
    "group2": {
    "name": "800 ms < t < 1200 ms",
    "count": 0,
    "percentage": 0
},
    "group3": {
    "name": "t > 1200 ms",
    "count": 0,
    "percentage": 0
},
    "group4": {
    "name": "failed",
    "count": 0,
    "percentage": 0
},
    "meanNumberOfRequestsPerSecond": {
        "total": 0.3333333333333333,
        "ok": 0.3333333333333333,
        "ko": 0
    }
}
    }
}

}